setup.py
dist_test_unnati/Binomialdistribution.py
dist_test_unnati/Gaussiandistribution.py
dist_test_unnati/Generaldistribution.py
dist_test_unnati/__init__.py
dist_test_unnati.egg-info/PKG-INFO
dist_test_unnati.egg-info/SOURCES.txt
dist_test_unnati.egg-info/dependency_links.txt
dist_test_unnati.egg-info/not-zip-safe
dist_test_unnati.egg-info/top_level.txt